[
  {
    "id": "media1",
    "title": "T.M.Revolution DVD Series The Summary -summarize 1-",
    "type": "DVD",
    "links": [
      "https://www.sonymusic.co.jp/artist/TMRevolution/discography/ESBL-2123",
      "https://www.amazon.co.jp/T-M-Revolution-DVD-Summary-summarize1/dp/B0000QX20E"
    ]
  },
  {
    "id": "media2",
    "title": "LIVE REVOLUTION COMPLETE EDITION-2 1996.6.6 赤坂BLITZ(FC限定VHS)",
    "type": "VHS",
    "links": []
  },
  {
    "id": "media3",
    "title": "無し",
    "type": "note",
    "links": []
  },
  {
    "id": "media4",
    "title": "LIVE REVOLUTION COMPLETE EDITION-3 1996.8.29 中野サンプラザ(FC限定VHS)",
    "type": "unknown",
    "links": []
  },
  {
    "id": "media5",
    "title": "T.M.Revolution DVD Series The Summary -summarize 2-",
    "type": "unknown",
    "links": []
  },
  {
    "id": "media6",
    "title": "T.M.Revolution DVD Series The Summary -summarize 3-",
    "type": "unknown",
    "links": []
  },
  {
    "id": "media7",
    "title": "T.M.Revolution DVD Series The Summary -summarize 4-",
    "type": "unknown",
    "links": []
  },
  {
    "id": "media8",
    "title": "the end of genesis T.M.R. evolution turbo type D LIVE ARENA 2000 A.D. Special DVD Version",
    "type": "unknown",
    "links": []
  },
  {
    "id": "media9",
    "title": "0001",
    "type": "unknown",
    "links": []
  },
  {
    "id": "media10",
    "title": "WOWOWで生中継してた・・・らしい",
    "type": "unknown",
    "links": []
  },
  {
    "id": "media11",
    "title": "無し（DVD化はARENA Tourのみ）",
    "type": "unknown",
    "links": []
  },
  {
    "id": "media12",
    "title": "T.M.R. LIVE REVOLUTION '02 B★E★S★T SUMMER CRUSH 2002",
    "type": "unknown",
    "links": []
  },
  {
    "id": "media13",
    "title": "SONIC WARP the Visual Fields",
    "type": "note",
    "links": []
  },
  {
    "id": "media14",
    "title": "T.M.Revolution SEVENTH HEAVEN T.M.R. LIVE REVOLUTION'04",
    "type": "note",
    "links": []
  },
  {
    "id": "media15",
    "title": "T.M.R. LIVE REVOLUTION '05 -vertical infinity-（テレビ放送のみ）",
    "type": "unknown",
    "links": []
  },
  {
    "id": "media16",
    "title": "T.M.R. LIVE REVOLUTION '06 -UNDER:COVER-",
    "type": "note",
    "links": []
  },
  {
    "id": "media17",
    "title": "無し（DVD/BD化はARENA STYLE Versionのみ）",
    "type": "unknown",
    "links": []
  },
  {
    "id": "media18",
    "title": "UNDER:COVER（CD）",
    "type": "note",
    "links": []
  },
  {
    "id": "media19",
    "title": "T.M.R. LIVE REVOLUTION'11-12 -CLOUD NINE-（CD）",
    "type": "note",
    "links": []
  },
  {
    "id": "media20",
    "title": "T.M.R. LIVE REVOLUTION '06",
    "type": "note",
    "links": []
  },
  {
    "id": "media21",
    "title": "-UNDER:COVER-",
    "type": "note",
    "links": []
  },
  {
    "id": "media22",
    "title": "イナズマロックフェス 2011",
    "type": "note",
    "links": []
  },
  {
    "id": "media23",
    "title": "T.M.R. LIVE REVOLUTION '11 -Strikes Back IX- in ニコファーレ",
    "type": "note",
    "links": []
  },
  {
    "id": "media24",
    "title": "T.M.R. LIVE REVOLUTION '12 -15th Anniversary FINAL-",
    "type": "note",
    "links": []
  },
  {
    "id": "media25",
    "title": "T.M.R. LIVE REVOLUTION'13 -UNDER II COVER-",
    "type": "unknown",
    "links": []
  },
  {
    "id": "media26",
    "title": "T.M.R. LIVE REVOLUTION'14 -今まで（以下略）…'14-",
    "type": "note",
    "links": []
  },
  {
    "id": "media27",
    "title": "DOUBLE-DEAL（CD）完全生産限定盤A",
    "type": "note",
    "links": []
  },
  {
    "id": "media28",
    "title": "T.M.R. LIVE REVOLUTION '15 -Strikes Back XI-",
    "type": "note",
    "links": []
  },
  {
    "id": "media29",
    "title": "イナズマロックフェス 2015（テレビ放送のみ）",
    "type": "note",
    "links": []
  },
  {
    "id": "media30",
    "title": "T.M.R. LIVE REVOLUTION'16-'17 -Route 20- LIVE AT NIPPON BUDOKAN",
    "type": "note",
    "links": []
  },
  {
    "id": "media31",
    "title": "T.M.R. LIVE REVOLUTION'17 -ROUND HOUSE CUTBACK-（CD）",
    "type": "unknown",
    "links": []
  },
  {
    "id": "media32",
    "title": "イナズマロックフェス 2017",
    "type": "note",
    "links": []
  },
  {
    "id": "media33",
    "title": "T.M.R. LIVE REVOLUTION '17 -20th Anniversary FINAL at Saitama Super Arena-",
    "type": "unknown",
    "links": []
  },
  {
    "id": "media34",
    "title": "無し（DVD/BD化はVOTE JAPANのみ）",
    "type": "unknown",
    "links": []
  },
  {
    "id": "media35",
    "title": "T.M.Revolution西川貴教さんのライブに突撃してみた！【HOT LIMIT】【HIGH PRESSURE】（ガチャピンちゃんねる）",
    "type": "note",
    "links": []
  },
  {
    "id": "media36",
    "title": "the 25th Anniversary：T.M.R. LIVE REVOLUTION'21 -VOTE- Extended Live Edition（配信ライブ）",
    "type": "note",
    "links": []
  },
  {
    "id": "media37",
    "title": "T.M.R. LIVE REVOLUTION'22-'23 -VOTE JAPAN-",
    "type": "note",
    "links": []
  }
]